n2cw/__init__.py
n2cw/aws.py
n2cw/cli.py
n2cw/metrics.py
n2cw-0.1.2.dist-info/DESCRIPTION.rst
n2cw-0.1.2.dist-info/entry_points.txt
n2cw-0.1.2.dist-info/METADATA
n2cw-0.1.2.dist-info/metadata.json
n2cw-0.1.2.dist-info/RECORD
n2cw-0.1.2.dist-info/top_level.txt
n2cw-0.1.2.dist-info/WHEEL
