Metadata-Version: 2.0
Name: n2cw
Version: 0.1.2
Summary: A wrapper for sending Nagios plugin output to CloudWatch
Home-page: http://github.com/slank/n2cw
Author: Matthew Wedgwood
Author-email: mwedgwood@gmail.com
License: MIT
Keywords: amazon,aws,cloudwatch,nagios,metrics,monitoring
Platform: UNKNOWN
Classifier: Development Status :: 3 - Alpha
Classifier: Topic :: Utilities
Classifier: License :: OSI Approved :: MIT License
Requires-Dist: botocore (>=0.80.0)
